origen_metal/__init__.py
origen_metal/_helpers/__init__.py
origen_metal/_helpers/interactive.py
origen_metal/_origen_metal.pyd
origen_metal/framework/__init__.py
origen_metal/framework/reference_files.py
origen_metal/framework/users.py
origen_metal/frontend/__init__.py
origen_metal/frontend/data_store_api.py
origen_metal/frontend/data_store_view.py
origen_metal/prog_gen/__init__.py
origen_metal/prog_gen/test_ids.py
origen_metal/py.typed
origen_metal/utils/__init__.py
origen_metal/utils/differ.py
origen_metal/utils/ldap.py
origen_metal/utils/mailer.py
origen_metal/utils/param_str.py
origen_metal/utils/revision_control/__init__.py
origen_metal/utils/revision_control/supported/__init__.py
origen_metal/utils/revision_control/supported/git.py
origen_metal/utils/version.py
origen_metal-1.1.0.dist-info/METADATA
origen_metal-1.1.0.dist-info/WHEEL
origen_metal-1.1.0.dist-info/RECORD
