Metadata-Version: 2.1
Name: origen-metal
Version: 1.1.0
Summary: Bare metal APIs for the Origen SDK
Home-page: https://origen-sdk.org/o2
License: MIT
Author: Origen-SDK
Requires-Python: >=3.7.0,<3.13
Classifier: License :: OSI Approved :: MIT License
Classifier: Programming Language :: Python :: 3
Classifier: Programming Language :: Python :: 3.7
Classifier: Programming Language :: Python :: 3.8
Classifier: Programming Language :: Python :: 3.9
Classifier: Programming Language :: Python :: 3.10
Classifier: Programming Language :: Python :: 3.11
Requires-Dist: colorama (>=0.4.4)
Requires-Dist: importlib-metadata (>=6.7.0)
Requires-Dist: pyreadline3 (>=3.3,<4.0) ; sys_platform == "win32"
Requires-Dist: termcolor (>=1.1.0)
